[
  {
    "type": "image",
    "text": "Угадайте флаг страны",
    "answer": "Сейшелы",
    "file": "Сейшелы.gif",
    "points": 100
  },
  {
    "type": "image",
    "text": "Угадайте флаг страны",
    "answer": "Афганистан",
    "file": "Афганистан.gif",
    "points": 200
  },
  {
    "type": "image",
    "text": "Угадайте флаг страны",
    "answer": "Румыния",
    "file": "",
    "points": 300
  },
  {
    "type": "image",
    "text": "Угадайте флаг страны",
    "answer": "Таджикистан",
    "file": "Таджикистан.gif",
    "points": 400
  },
  {
    "type": "image",
    "text": "Угадайте флаг страны",
    "answer": "Уганда",
    "file": "Уганда.gif",
    "points": 500
  },
  {
    "type": "music",
    "text": "Назовите оригинального исполнителя песни",
    "answer": "Бритни Спирс",
    "file": "britney.mp3",
    "points": 100
  },
  {
    "type": "image",
    "text": "Назовите фильм",
    "answer": "Пианист",
    "file": "пианист.jpg",
    "points": 200
  },
  {
    "type": "image",
    "text": "Назовите сериал",
    "answer": "Сотня",
    "file": "сотня.jpg",
    "points": 300
  },
  {
    "type": "text",
    "text": "Сидит дед, в шубу одет, Кто его раздевает, тот слезы проливает",
    "answer": "Лук",
    "points": 400
  }
]